confclass.py
confclass-0.1.2.dist-info/LICENSE
confclass-0.1.2.dist-info/METADATA
confclass-0.1.2.dist-info/WHEEL
confclass-0.1.2.dist-info/top_level.txt
confclass-0.1.2.dist-info/RECORD
